portableqda/__init__.py
portableqda/__main__.py
portableqda/refi_qda.py
tests/REFI-QDA-1-5.qdc
tests/__init__.py
tests/__main__.py
tests/doorstop-core-tests-files-exported.qdc
tests/portableQDA_Atlasti.qdc
tests/portableQDA_test_compare_Diff_destAtlas.qdc
tests/test_portableqda.py
tests/test_refi_qda.py
portableqda-0.4.2.dist-info/entry_points.txt
portableqda-0.4.2.dist-info/LICENSE.md
portableqda-0.4.2.dist-info/WHEEL
portableqda-0.4.2.dist-info/METADATA
portableqda-0.4.2.dist-info/RECORD
