Metadata-Version: 2.1
Name: portableqda
Version: 0.4.2
Summary: round-trip information exchange using the REFI-QDA standard for Qualitative Research: codebooks (QDC files) and QDPX projects, as per https://www.qdasoftware.org
Home-page: https://gitlab.com/portableqda/portableQDA
License: LGPL-3.0-only
Keywords: Qualitative Research,Qualitative-Data-Analysis,QDA,QDC file format,QDPX file format,codebook,CAQDAS
Author: Leandro Batlle
Author-email: Leandro.Batlle@gmail.com
Requires-Python: >=3.6,<4.0
Classifier: Development Status :: 3 - Alpha
Classifier: Environment :: Console
Classifier: Intended Audience :: Developers
Classifier: Intended Audience :: Education
Classifier: Intended Audience :: Science/Research
Classifier: License :: OSI Approved :: GNU Lesser General Public License v3 (LGPLv3)
Classifier: Operating System :: OS Independent
Classifier: Programming Language :: Python
Classifier: Programming Language :: Python :: 3
Classifier: Programming Language :: Python :: 3.6
Classifier: Programming Language :: Python :: 3.7
Classifier: Programming Language :: Python :: 3.8
Classifier: Programming Language :: Python :: 3.9
Classifier: Topic :: Documentation
Classifier: Topic :: Sociology
Classifier: Topic :: Software Development :: Libraries
Classifier: Topic :: Text Processing :: Markup :: XML
Requires-Dist: lxml (>=4.6.2,<5.0.0)
Requires-Dist: nose (>=1.3.7,<2.0.0)
Requires-Dist: xmldiff (>=2.4,<3.0)
Project-URL: Documentation, https://gitlab.com/portableqda/portableQDA/-/wikis/home
Project-URL: Repository, https://gitlab.com/portableqda/portableQDA
